weavster/__init__.py
weavster/foo.py
weavster-0.0.0.dist-info/METADATA
weavster-0.0.0.dist-info/WHEEL
weavster-0.0.0.dist-info/licenses/LICENSE
weavster-0.0.0.dist-info/RECORD
