Metadata-Version: 2.4
Name: weavster
Version: 0.0.0
Summary: Weavster is a cloud-native integration platform that brings declarative simplicity to data pipelines of all sizes.
Project-URL: Homepage, https://weavster-dev.github.io/weavster/
Project-URL: Repository, https://github.com/weavster-dev/weavster
Project-URL: Documentation, https://weavster-dev.github.io/weavster/
Author-email: Gregory Hunt <huntg1@gmail.com>
License-File: LICENSE
Keywords: python
Classifier: Intended Audience :: Developers
Classifier: Programming Language :: Python
Classifier: Programming Language :: Python :: 3
Classifier: Programming Language :: Python :: 3.9
Classifier: Programming Language :: Python :: 3.10
Classifier: Programming Language :: Python :: 3.11
Classifier: Programming Language :: Python :: 3.12
Classifier: Programming Language :: Python :: 3.13
Classifier: Topic :: Software Development :: Libraries :: Python Modules
Requires-Python: <4.0,>=3.9
